lxdock/__init__.py
lxdock/client.py
lxdock/constants.py
lxdock/container.py
lxdock/exceptions.py
lxdock/logging.py
lxdock/network.py
lxdock/project.py
lxdock/cli/__init__.py
lxdock/cli/constants.py
lxdock/cli/exceptions.py
lxdock/cli/main.py
lxdock/cli/project.py
lxdock/cli/utils.py
lxdock/conf/__init__.py
lxdock/conf/config.py
lxdock/conf/constants.py
lxdock/conf/exceptions.py
lxdock/conf/interpolation.py
lxdock/conf/schema.py
lxdock/conf/validators.py
lxdock/guests/__init__.py
lxdock/guests/alpine.py
lxdock/guests/archlinux.py
lxdock/guests/base.py
lxdock/guests/centos.py
lxdock/guests/debian.py
lxdock/guests/fedora.py
lxdock/guests/gentoo.py
lxdock/guests/opensuse.py
lxdock/guests/oracle.py
lxdock/guests/ubuntu.py
lxdock/hosts/__init__.py
lxdock/hosts/base.py
lxdock/provisioners/__init__.py
lxdock/provisioners/ansible.py
lxdock/provisioners/base.py
lxdock/provisioners/puppet.py
lxdock/provisioners/shell.py
lxdock/test/__init__.py
lxdock/test/fakes.py
lxdock/test/fixtures.py
lxdock/test/testcases.py
lxdock/utils/__init__.py
lxdock/utils/identifier.py
lxdock/utils/lxd.py
lxdock/utils/metaclass.py
lxdock-0.4.1.dist-info/DESCRIPTION.rst
lxdock-0.4.1.dist-info/LICENSE.txt
lxdock-0.4.1.dist-info/METADATA
lxdock-0.4.1.dist-info/RECORD
lxdock-0.4.1.dist-info/WHEEL
lxdock-0.4.1.dist-info/entry_points.txt
lxdock-0.4.1.dist-info/metadata.json
lxdock-0.4.1.dist-info/top_level.txt
