Metadata-Version: 2.0
Name: lxdock
Version: 0.4.1
Summary: LXDock is a tool for orchestrating LXD containers.
Home-page: https://github.com/lxdock/lxdock
Author: Virgil Dupras, Morgan Aubert
Author-email: UNKNOWN
License: GPLv3
Keywords: lxd lxc containers environments orchestration devops
Platform: UNKNOWN
Classifier: Development Status :: 4 - Beta
Classifier: Environment :: Console
Classifier: Intended Audience :: Developers
Classifier: License :: OSI Approved :: GNU General Public License v3 (GPLv3)
Classifier: Natural Language :: English
Classifier: Programming Language :: Python
Classifier: Programming Language :: Python :: 3
Classifier: Programming Language :: Python :: 3.4
Classifier: Programming Language :: Python :: 3.5
Classifier: Programming Language :: Python :: 3.6
Requires-Dist: PyYAML (<4.0,>=3.0)
Requires-Dist: colorlog (<3.0,>=2.0)
Requires-Dist: pylxd (>=2.2.4)
Requires-Dist: python-dotenv (>=0.6)
Requires-Dist: voluptuous (>=0.9,<1.0)
